coordinate_converter/__init__.py
coordinate_converter/coordinate_converter.py
wgstolest-1.0.dist-info/METADATA
wgstolest-1.0.dist-info/WHEEL
wgstolest-1.0.dist-info/top_level.txt
wgstolest-1.0.dist-info/RECORD
