Metadata-Version: 2.2
Name: wgstolest
Version: 1.0
Requires-Dist: pyproj
Dynamic: requires-dist
